{
  "minecraft:white_concrete": "minecraft:white_concrete",
  "minecraft:orange_concrete": "minecraft:orange_concrete",
  "minecraft:magenta_concrete": "minecraft:magenta_concrete",
  "minecraft:light_blue_concrete": "minecraft:light_blue_concrete",
  "minecraft:yellow_concrete": "minecraft:yellow_concrete",
  "minecraft:lime_concrete": "minecraft:lime_concrete",
  "minecraft:pink_concrete": "minecraft:pink_concrete",
  "minecraft:gray_concrete": "minecraft:gray_concrete",
  "minecraft:light_gray_concrete": "minecraft:light_gray_concrete",
  "minecraft:cyan_concrete": "minecraft:cyan_concrete",
  "minecraft:purple_concrete": "minecraft:purple_concrete",
  "minecraft:blue_concrete": "minecraft:blue_concrete",
  "minecraft:brown_concrete": "minecraft:brown_concrete",
  "minecraft:green_concrete": "minecraft:green_concrete",
  "minecraft:red_concrete":"minecraft:red_concrete",
  "minecraft:black_concrete": "minecraft:black_concrete",
  "minecraft:white_shulker_box[facing=north]": "minecraft:white_shulker_box",
  "minecraft:white_shulker_box[facing=east]": "minecraft:white_shulker_box",
  "minecraft:white_shulker_box[facing=south]": "minecraft:white_shulker_box",
  "minecraft:white_shulker_box[facing=west]": "minecraft:white_shulker_box",
  "minecraft:white_shulker_box[facing=up]": "minecraft:white_shulker_box",
  "minecraft:white_shulker_box[facing=down]": "minecraft:white_shulker_box",
  "minecraft:orange_shulker_box[facing=north]": "minecraft:orange_shulker_box",
  "minecraft:orange_shulker_box[facing=east]": "minecraft:orange_shulker_box",
  "minecraft:orange_shulker_box[facing=south]": "minecraft:orange_shulker_box",
  "minecraft:orange_shulker_box[facing=west]": "minecraft:orange_shulker_box",
  "minecraft:orange_shulker_box[facing=up]": "minecraft:orange_shulker_box",
  "minecraft:orange_shulker_box[facing=down]": "minecraft:orange_shulker_box",
  "minecraft:magenta_shulker_box[facing=north]": "minecraft:magenta_shulker_box",
  "minecraft:magenta_shulker_box[facing=east]": "minecraft:magenta_shulker_box",
  "minecraft:magenta_shulker_box[facing=south]": "minecraft:magenta_shulker_box",
  "minecraft:magenta_shulker_box[facing=west]": "minecraft:magenta_shulker_box",
  "minecraft:magenta_shulker_box[facing=up]": "minecraft:magenta_shulker_box",
  "minecraft:magenta_shulker_box[facing=down]": "minecraft:magenta_shulker_box",
  "minecraft:light_blue_shulker_box[facing=north]": "minecraft:light_blue_shulker_box",
  "minecraft:light_blue_shulker_box[facing=east]": "minecraft:light_blue_shulker_box",
  "minecraft:light_blue_shulker_box[facing=south]": "minecraft:light_blue_shulker_box",
  "minecraft:light_blue_shulker_box[facing=west]": "minecraft:light_blue_shulker_box",
  "minecraft:light_blue_shulker_box[facing=up]": "minecraft:light_blue_shulker_box",
  "minecraft:light_blue_shulker_box[facing=down]": "minecraft:light_blue_shulker_box",
  "minecraft:yellow_shulker_box[facing=north]": "minecraft:yellow_shulker_box",
  "minecraft:yellow_shulker_box[facing=east]": "minecraft:yellow_shulker_box",
  "minecraft:yellow_shulker_box[facing=south]": "minecraft:yellow_shulker_box",
  "minecraft:yellow_shulker_box[facing=west]": "minecraft:yellow_shulker_box",
  "minecraft:yellow_shulker_box[facing=up]": "minecraft:yellow_shulker_box",
  "minecraft:yellow_shulker_box[facing=down]": "minecraft:yellow_shulker_box",
  "minecraft:lime_shulker_box[facing=north]": "minecraft:lime_shulker_box",
  "minecraft:lime_shulker_box[facing=east]": "minecraft:lime_shulker_box",
  "minecraft:lime_shulker_box[facing=south]": "minecraft:lime_shulker_box",
  "minecraft:lime_shulker_box[facing=west]": "minecraft:lime_shulker_box",
  "minecraft:lime_shulker_box[facing=up]": "minecraft:lime_shulker_box",
  "minecraft:lime_shulker_box[facing=down]": "minecraft:lime_shulker_box",
  "minecraft:pink_shulker_box[facing=north]": "minecraft:pink_shulker_box",
  "minecraft:pink_shulker_box[facing=east]": "minecraft:pink_shulker_box",
  "minecraft:pink_shulker_box[facing=south]": "minecraft:pink_shulker_box",
  "minecraft:pink_shulker_box[facing=west]": "minecraft:pink_shulker_box",
  "minecraft:pink_shulker_box[facing=up]": "minecraft:pink_shulker_box",
  "minecraft:pink_shulker_box[facing=down]": "minecraft:pink_shulker_box",
  "minecraft:gray_shulker_box[facing=north]": "minecraft:gray_shulker_box",
  "minecraft:gray_shulker_box[facing=east]": "minecraft:gray_shulker_box",
  "minecraft:gray_shulker_box[facing=south]": "minecraft:gray_shulker_box",
  "minecraft:gray_shulker_box[facing=west]": "minecraft:gray_shulker_box",
  "minecraft:gray_shulker_box[facing=up]": "minecraft:gray_shulker_box",
  "minecraft:gray_shulker_box[facing=down]": "minecraft:gray_shulker_box",
  "minecraft:light_gray_shulker_box[facing=north]": "minecraft:light_gray_shulker_box",
  "minecraft:light_gray_shulker_box[facing=east]": "minecraft:light_gray_shulker_box",
  "minecraft:light_gray_shulker_box[facing=south]": "minecraft:light_gray_shulker_box",
  "minecraft:light_gray_shulker_box[facing=west]": "minecraft:light_gray_shulker_box",
  "minecraft:light_gray_shulker_box[facing=up]": "minecraft:light_gray_shulker_box",
  "minecraft:light_gray_shulker_box[facing=down]": "minecraft:light_gray_shulker_box",
  "minecraft:cyan_shulker_box[facing=north]": "minecraft:cyan_shulker_box",
  "minecraft:cyan_shulker_box[facing=east]": "minecraft:cyan_shulker_box",
  "minecraft:cyan_shulker_box[facing=south]": "minecraft:cyan_shulker_box",
  "minecraft:cyan_shulker_box[facing=west]": "minecraft:cyan_shulker_box",
  "minecraft:cyan_shulker_box[facing=up]": "minecraft:cyan_shulker_box",
  "minecraft:cyan_shulker_box[facing=down]": "minecraft:cyan_shulker_box",
  "minecraft:purple_shulker_box[facing=north]": "minecraft:purple_shulker_box",
  "minecraft:purple_shulker_box[facing=east]": "minecraft:purple_shulker_box",
  "minecraft:purple_shulker_box[facing=south]": "minecraft:purple_shulker_box",
  "minecraft:purple_shulker_box[facing=west]": "minecraft:purple_shulker_box",
  "minecraft:purple_shulker_box[facing=up]": "minecraft:purple_shulker_box",
  "minecraft:purple_shulker_box[facing=down]": "minecraft:purple_shulker_box",
  "minecraft:blue_shulker_box[facing=north]": "minecraft:blue_shulker_box",
  "minecraft:blue_shulker_box[facing=east]": "minecraft:blue_shulker_box",
  "minecraft:blue_shulker_box[facing=south]": "minecraft:blue_shulker_box",
  "minecraft:blue_shulker_box[facing=west]": "minecraft:blue_shulker_box",
  "minecraft:blue_shulker_box[facing=up]": "minecraft:blue_shulker_box",
  "minecraft:blue_shulker_box[facing=down]": "minecraft:blue_shulker_box",
  "minecraft:brown_shulker_box[facing=north]": "minecraft:brown_shulker_box",
  "minecraft:brown_shulker_box[facing=east]": "minecraft:brown_shulker_box",
  "minecraft:brown_shulker_box[facing=south]": "minecraft:brown_shulker_box",
  "minecraft:brown_shulker_box[facing=west]": "minecraft:brown_shulker_box",
  "minecraft:brown_shulker_box[facing=up]": "minecraft:brown_shulker_box",
  "minecraft:brown_shulker_box[facing=down]": "minecraft:brown_shulker_box",
  "minecraft:green_shulker_box[facing=north]": "minecraft:green_shulker_box",
  "minecraft:green_shulker_box[facing=east]": "minecraft:green_shulker_box",
  "minecraft:green_shulker_box[facing=south]": "minecraft:green_shulker_box",
  "minecraft:green_shulker_box[facing=west]": "minecraft:green_shulker_box",
  "minecraft:green_shulker_box[facing=up]": "minecraft:green_shulker_box",
  "minecraft:green_shulker_box[facing=down]": "minecraft:green_shulker_box",
  "minecraft:red_shulker_box[facing=north]": "minecraft:red_shulker_box",
  "minecraft:red_shulker_box[facing=east]": "minecraft:red_shulker_box",
  "minecraft:red_shulker_box[facing=south]": "minecraft:red_shulker_box",
  "minecraft:red_shulker_box[facing=west]": "minecraft:red_shulker_box",
  "minecraft:red_shulker_box[facing=up]": "minecraft:red_shulker_box",
  "minecraft:red_shulker_box[facing=down]": "minecraft:red_shulker_box",
  "minecraft:black_shulker_box[facing=north]": "minecraft:black_shulker_box",
  "minecraft:black_shulker_box[facing=east]": "minecraft:black_shulker_box",
  "minecraft:black_shulker_box[facing=south]": "minecraft:black_shulker_box",
  "minecraft:black_shulker_box[facing=west]": "minecraft:black_shulker_box",
  "minecraft:black_shulker_box[facing=up]": "minecraft:black_shulker_box",
  "minecraft:black_shulker_box[facing=down]": "minecraft:black_shulker_box",
  "minecraft:observer[facing=north,powered=true]": "minecraft:observer[minecraft:facing_direction=north,powered_bit=true]",
  "minecraft:observer[facing=north,powered=false]": "minecraft:observer[minecraft:facing_direction=north,powered_bit=false]",
  "minecraft:observer[facing=east,powered=true]": "minecraft:observer[minecraft:facing_direction=east,powered_bit=true]",
  "minecraft:observer[facing=east,powered=false]": "minecraft:observer[minecraft:facing_direction=east,powered_bit=false]",
  "minecraft:observer[facing=south,powered=true]": "minecraft:observer[minecraft:facing_direction=south,powered_bit=true]",
  "minecraft:observer[facing=south,powered=false]": "minecraft:observer[minecraft:facing_direction=south,powered_bit=false]",
  "minecraft:observer[facing=west,powered=true]": "minecraft:observer[minecraft:facing_direction=west,powered_bit=true]",
  "minecraft:observer[facing=west,powered=false]": "minecraft:observer[minecraft:facing_direction=west,powered_bit=false]",
  "minecraft:observer[facing=up,powered=true]": "minecraft:observer[minecraft:facing_direction=up,powered_bit=true]",
  "minecraft:observer[facing=up,powered=false]": "minecraft:observer[minecraft:facing_direction=up,powered_bit=false]",
  "minecraft:observer[facing=down,powered=true]": "minecraft:observer[minecraft:facing_direction=down,powered_bit=true]",
  "minecraft:observer[facing=down,powered=false]": "minecraft:observer[minecraft:facing_direction=down,powered_bit=false]"
}